jupyter_secrets_manager/__init__.py
jupyter_secrets_manager/_version.py
jupyter_secrets_manager-0.4.0.data/data/share/jupyter/labextensions/jupyter-secrets-manager/package.json
jupyter_secrets_manager-0.4.0.data/data/share/jupyter/labextensions/jupyter-secrets-manager/schemas/jupyter-secrets-manager/manager.json
jupyter_secrets_manager-0.4.0.data/data/share/jupyter/labextensions/jupyter-secrets-manager/schemas/jupyter-secrets-manager/package.json.orig
jupyter_secrets_manager-0.4.0.data/data/share/jupyter/labextensions/jupyter-secrets-manager/static/728.69cdb8043c4eb7a36084.js
jupyter_secrets_manager-0.4.0.data/data/share/jupyter/labextensions/jupyter-secrets-manager/static/810.fbdfc5a62015cce3d70b.js
jupyter_secrets_manager-0.4.0.data/data/share/jupyter/labextensions/jupyter-secrets-manager/static/remoteEntry.c7854c8222ab48705366.js
jupyter_secrets_manager-0.4.0.data/data/share/jupyter/labextensions/jupyter-secrets-manager/static/style.js
jupyter_secrets_manager-0.4.0.data/data/share/jupyter/labextensions/jupyter-secrets-manager/static/third-party-licenses.json
jupyter_secrets_manager-0.4.0.data/data/share/jupyter/labextensions/jupyter-secrets-manager/install.json
jupyter_secrets_manager-0.4.0.dist-info/METADATA
jupyter_secrets_manager-0.4.0.dist-info/WHEEL
jupyter_secrets_manager-0.4.0.dist-info/licenses/LICENSE
jupyter_secrets_manager-0.4.0.dist-info/RECORD
